RMDL/BuildModel.py
RMDL/Global.py
RMDL/Plot.py
RMDL/RMDL_Image.py
RMDL/RMDL_Text.py
RMDL/__init__.py
RMDL/text_feature_extraction.py
RMDL/Download/Download_Glove.py
RMDL/Download/Download_WOS.py
RMDL/Download/__init__.py
RMDL-1.0.8.dist-info/LICENSE
RMDL-1.0.8.dist-info/METADATA
RMDL-1.0.8.dist-info/WHEEL
RMDL-1.0.8.dist-info/top_level.txt
RMDL-1.0.8.dist-info/RECORD
