Metadata-Version: 2.1
Name: RMDL
Version: 1.0.8
Summary: RMDL: Random Multimodel Deep Learning for Classification
Home-page: https://github.com/kk7nc/RMDL
Author: Kamran Kowsari
Author-email: kk7nc@virginia.edu
License: UNKNOWN
Platform: UNKNOWN
Classifier: Programming Language :: Python :: 3.7
Classifier: Programming Language :: Python :: 3.6
Classifier: Programming Language :: Python :: 3.5
Classifier: Programming Language :: Python :: 3.4
Classifier: Environment :: Console
Classifier: Intended Audience :: Science/Research
Classifier: Intended Audience :: Education
Classifier: Intended Audience :: Information Technology
Classifier: License :: OSI Approved :: GNU General Public License v3 or later (GPLv3+)
Classifier: Operating System :: OS Independent
Classifier: Topic :: Software Development :: Libraries
Classifier: Topic :: Software Development :: Libraries :: Python Modules
Classifier: Topic :: Scientific/Engineering :: Artificial Intelligence
Classifier: Topic :: Scientific/Engineering :: Information Analysis
Classifier: Topic :: Scientific/Engineering :: Image Recognition
Classifier: Topic :: Text Editors :: Text Processing
Requires-Dist: matplotlib (>=2.1.2)
Requires-Dist: numpy (>=1.12.1)
Requires-Dist: pandas (>=0.22.0)
Requires-Dist: scipy
Requires-Dist: tensorflow
Requires-Dist: keras (>=2.0.9)
Requires-Dist: scikit-learn (>=0.19.0)
Requires-Dist: nltk (>=3.2.4)
